{
  "todos": [
    {
      "subject": "ㄴ",
      "completed": false,
      "id": 8
    },
    {
      "subject": "ㄹ",
      "completed": false,
      "id": 9
    },
    {
      "subject": "sdsd",
      "completed": false,
      "id": 10
    },
    {
      "subject": "sdsd",
      "completed": false,
      "id": 11
    },
    {
      "subject": "sdsd",
      "completed": false,
      "id": 12
    },
    {
      "subject": "sdsd",
      "completed": false,
      "id": 13
    },
    {
      "subject": "ㅇㄴㄹㅇㄹ",
      "completed": false,
      "id": 14
    },
    {
      "subject": "1",
      "completed": false,
      "id": 15
    },
    {
      "subject": "2",
      "completed": false,
      "id": 16
    },
    {
      "subject": "3",
      "completed": false,
      "id": 17
    },
    {
      "subject": "4",
      "completed": false,
      "id": 18
    },
    {
      "subject": "5",
      "completed": false,
      "id": 19
    },
    {
      "subject": "6",
      "completed": false,
      "id": 20
    },
    {
      "subject": "7",
      "completed": false,
      "id": 21
    },
    {
      "subject": "8",
      "completed": false,
      "id": 22
    },
    {
      "subject": "ㅇㄴㄹ",
      "completed": false,
      "id": 23
    },
    {
      "subject": "ㄴㅁㅇㅁㄴ",
      "completed": false,
      "id": 24
    },
    {
      "subject": "ㄴㅁㅇㅁㄴㅇ",
      "completed": false,
      "id": 25
    },
    {
      "subject": "ㅁㄴㅇㅁㄴㅇ",
      "completed": false,
      "id": 26
    },
    {
      "subject": "ㅁㅇㄴ",
      "completed": false,
      "id": 27
    },
    {
      "subject": "buy milk",
      "completed": false,
      "id": 28
    }
  ]
}